cli/__init__.py
cli/cli.py
cli/commands.py
cli/errors.py
cli/py.typed
cli/ext/__init__.py
cli/ext/shard.py
create_a_cli_tool-0.5.4.dist-info/LICENSE
create_a_cli_tool-0.5.4.dist-info/METADATA
create_a_cli_tool-0.5.4.dist-info/WHEEL
create_a_cli_tool-0.5.4.dist-info/top_level.txt
create_a_cli_tool-0.5.4.dist-info/RECORD
